MarkdownViewer/MarkdownViewer.py
MarkdownViewer/__init__.py
MarkdownViewer/highlight_js.html
MarkdownViewer/place_holder.md
gMarkdownViewer-0.0.3.dist-info/LICENSE.md
gMarkdownViewer-0.0.3.dist-info/METADATA
gMarkdownViewer-0.0.3.dist-info/WHEEL
gMarkdownViewer-0.0.3.dist-info/entry_points.txt
gMarkdownViewer-0.0.3.dist-info/top_level.txt
gMarkdownViewer-0.0.3.dist-info/RECORD
