Metadata-Version: 2.1
Name: gMarkdownViewer
Version: 0.0.3
Summary: A simple GUI application for viewing Markdown files.
Home-page: https://git.benknisley.com/benknisley/MarkdownViewer
Author: Ben Knisley
Author-email: benknisley@gmail.com
License: MIT
Keywords: markdown
Platform: UNKNOWN
Classifier: Programming Language :: Python :: 3.9
Requires-Dist: Markdown (==3.3.4)
Requires-Dist: PyGObject (==3.40.1)
